fcbusquestx/__init__.py
fcbusquestx-0.1.dist-info/METADATA
fcbusquestx-0.1.dist-info/WHEEL
fcbusquestx-0.1.dist-info/top_level.txt
fcbusquestx-0.1.dist-info/RECORD
